decache-0.1.7.dist-info/METADATA
decache-0.1.7.dist-info/WHEEL
decache-0.1.7.dist-info/entry_points.txt
decache/__init__.py
decache/store_backend/__init__.py
decache/store_backend/fs_store.py
decache/store_backend/types.py
decache/utils/__init__.py
decache/utils/helper.py
decache-0.1.7.dist-info/RECORD
