Metadata-Version: 2.1
Name: decache
Version: 0.1.7
Summary: A custom store backend for `joblib` that de-duplicates large NumPy arrays to save significant disk space in scientific computing and machine learning workflows.
Author-Email: "TX.Mao" <mtianxiang@gmail.com>
License: MIT
Requires-Python: >=3.12
Requires-Dist: loguru>=0.7.0
Requires-Dist: joblib>=1.5.2
Requires-Dist: numpy>=2.2.2
